growbuddies/PID_code.py
growbuddies/__init__.py
growbuddies/__main__.py
growbuddies/calibrate_dripbuddy.py
growbuddies/colors.py
growbuddies/ez_humidity_adjust.py
growbuddies/growbuddies_settings.json
growbuddies/influxdb_code.py
growbuddies/logginghandler.py
growbuddies/maintain_vpd.py
growbuddies/manage_vpd.py
growbuddies/mistbuddy_code.py
growbuddies/mqtt_code.py
growbuddies/settings_code.py
growbuddies/snifferbuddyreadings_code.py
growbuddies/test.py
growbuddies/data/__init__.py
growbuddies/tests/__init__.py
growbuddies/tests/test_gus.py
growbuddies/tests/test_mqtt_code.py
growbuddies-2022.12.9.dist-info/METADATA
growbuddies-2022.12.9.dist-info/WHEEL
growbuddies-2022.12.9.dist-info/entry_points.txt
growbuddies-2022.12.9.dist-info/top_level.txt
growbuddies-2022.12.9.dist-info/RECORD
