Metadata-Version: 2.1
Name: growbuddies
Version: 2022.12.9
Summary: Buddies to help maximize the growth of plants in your indoor garden.
Project-URL: Homepage, https://github.com/solarslurpi/GrowBuddies
Requires-Dist: influxdb (~=5.3.1)
Requires-Dist: paho-mqtt (~=1.6.1)
